RoboDnsRecon.py
RoboDnsRecon-1.0.dist-info/DESCRIPTION.rst
RoboDnsRecon-1.0.dist-info/METADATA
RoboDnsRecon-1.0.dist-info/RECORD
RoboDnsRecon-1.0.dist-info/WHEEL
RoboDnsRecon-1.0.dist-info/metadata.json
RoboDnsRecon-1.0.dist-info/top_level.txt
