Metadata-Version: 2.0
Name: RoboDnsRecon
Version: 1.0
Summary: Robot Framework Library for DNS Recon
Home-page: https://github.com/we45/RoboDnsRecon
Author: we45
Author-email: info@we45.com
License: MIT
Platform: UNKNOWN
Requires-Dist: docker
Requires-Dist: robotframework (==3.0.4)
